blocksat_gui-2.5.1.data/data/share/applications/blocksatgui.desktop
blocksat_gui-2.5.1.data/data/share/icons/blocksaticon.svg
blocksatcli/__init__.py
blocksatcli/__main__.py
blocksatcli/bitcoin.py
blocksatcli/cache.py
blocksatcli/config.py
blocksatcli/currency.py
blocksatcli/daemon_client.py
blocksatcli/defs.py
blocksatcli/dependencies.py
blocksatcli/firewall.py
blocksatcli/gqrx.py
blocksatcli/instructions.py
blocksatcli/ip.py
blocksatcli/main.py
blocksatcli/monitoring.py
blocksatcli/monitoring_api.py
blocksatcli/rp.py
blocksatcli/satip.py
blocksatcli/sdr.py
blocksatcli/standalone.py
blocksatcli/test_bitcoin.py
blocksatcli/test_cache.py
blocksatcli/test_config.py
blocksatcli/test_firewall.py
blocksatcli/test_gqrx.py
blocksatcli/test_helpers.py
blocksatcli/test_monitoring.py
blocksatcli/test_monitoring_api.py
blocksatcli/test_satip.py
blocksatcli/test_tsp.py
blocksatcli/test_update.py
blocksatcli/test_usb.py
blocksatcli/test_util.py
blocksatcli/tsp.py
blocksatcli/update.py
blocksatcli/upnp.py
blocksatcli/usb.py
blocksatcli/util.py
blocksatcli/verify_deps_instal.py
blocksatcli/api/__init__.py
blocksatcli/api/api.py
blocksatcli/api/bidding.py
blocksatcli/api/demorx.py
blocksatcli/api/error.py
blocksatcli/api/fec.py
blocksatcli/api/gpg.py
blocksatcli/api/invoice.py
blocksatcli/api/listen.py
blocksatcli/api/msg.py
blocksatcli/api/net.py
blocksatcli/api/order.py
blocksatcli/api/pkt.py
blocksatcli/api/test_bidding.py
blocksatcli/api/test_fec.py
blocksatcli/api/test_gpg.py
blocksatcli/api/test_listen.py
blocksatcli/api/test_msg.py
blocksatcli/api/test_net.py
blocksatcli/api/test_order.py
blocksatcli/api/test_pkt.py
blocksatcli/gpg/87D07253F69E4CD8629B0A21A94A007EC9D4458C.gpg
blocksatcli/mib/NOVRA-MIB.mib
blocksatcli/mib/NOVRA-s400-MIB.mib
blocksatcli/mib/RFC1155-SMI.txt
blocksatcli/mib/SNMPv2-CONF.txt
blocksatcli/mib/SNMPv2-SMI.txt
blocksatcli/mib/SNMPv2-TC.txt
blocksatgui/__init__.py
blocksatgui/app.py
blocksatgui/blocksatd.py
blocksatgui/config.py
blocksatgui/error.py
blocksat_gui-2.5.1.dist-info/LICENSE
blocksat_gui-2.5.1.dist-info/METADATA
blocksat_gui-2.5.1.dist-info/WHEEL
blocksat_gui-2.5.1.dist-info/entry_points.txt
blocksat_gui-2.5.1.dist-info/top_level.txt
blocksat_gui-2.5.1.dist-info/RECORD
