Metadata-Version: 2.1
Name: blocksat-gui
Version: 2.5.1
Summary: Blockstream Satellite GUI
Home-page: https://github.com/Blockstream/satellite
Author: Blockstream Corp
Author-email: satellite@blockstream.com
Classifier: Programming Language :: Python :: 3
Classifier: Programming Language :: Python :: 3 :: Only
Classifier: License :: OSI Approved :: GNU General Public License v3 (GPLv3)
Requires-Python: >=3
License-File: LICENSE
Requires-Dist: blocksat-cli ==2.5.1
Requires-Dist: pyside6 ==6.7.3
Provides-Extra: daemon
Requires-Dist: dbus-python ; extra == 'daemon'
